Geoparsing/Geoparsing.py
Geoparsing/__init__.py
Geoparsing/preprocessing_gazetteer.py
Geoparsing/gazetteer/features_campina.csv
Geoparsing/gazetteer/features_campina_ln.csv
Geoparsing/gazetteer/features_campina_pt.csv
Geoparsing/gazetteer/features_jp.csv
Geoparsing/gazetteer/features_jp_ln.csv
Geoparsing/gazetteer/features_jp_pt.csv
Geoparsing/gazetteer/features_paraiba.csv
Geoparsing/gazetteer/features_paraiba_ln.csv
Geoparsing/gazetteer/features_paraiba_pt.csv
Geoparsing/gazetteer/processados/gazetteer.csv
Geoparsing/gazetteer/processados/gazetteerpb.csv
Geoparsing/utils/__init__.py
Geoparsing/utils/utils.py
Pre_processamento/__init__.py
Pre_processamento/pre_processamento.py
TopicModeling/TopicModeling.py
TopicModeling/Train.py
TopicModeling/__init__.py
TopicModeling/modelo/meu_lda_model
TopicModeling/modelo/meu_lda_model.expElogbeta.npy
TopicModeling/modelo/meu_lda_model.id2word
TopicModeling/modelo/meu_lda_model.state
PyElit-0.1.0.dist-info/LICENSE
PyElit-0.1.0.dist-info/METADATA
PyElit-0.1.0.dist-info/WHEEL
PyElit-0.1.0.dist-info/top_level.txt
PyElit-0.1.0.dist-info/RECORD
