Metadata-Version: 2.1
Name: PyElit
Version: 0.1.0
Summary: Extraction of Locations and Issues of a Text
Home-page: https://github.com/Rickecr/PyElit
Author: Rich Elton
Author-email: richelton14@gmail.com
License: MIT
Project-URL: Código fonte, https://github.com/Rickecr/PyElit
Keywords: geoparsing topic modeling
Platform: UNKNOWN
